commonutils/__init__.py
commonutils/dictpopper.py
commonutils/serialport.py
commonutils/singleton.py
commonutils/staticutils.py
commonutils/version.py
simple_common_utils-0.11.0.dist-info/LICENSE
simple_common_utils-0.11.0.dist-info/METADATA
simple_common_utils-0.11.0.dist-info/WHEEL
simple_common_utils-0.11.0.dist-info/top_level.txt
simple_common_utils-0.11.0.dist-info/RECORD
