Metadata-Version: 2.1
Name: simple-common-utils
Version: 0.11.0
Summary: Common utils for python3 projects.
Home-page: https://github.com/RobinBobin/python3-common-utils
Author: Ruben Shalimov
Author-email: r_shalimov@inbox.ru
License: UNKNOWN
Platform: UNKNOWN
Classifier: Programming Language :: Python :: 3
Classifier: Operating System :: OS Independent
